README.md
setup.cfg
setup.py
cbastats/GameStats.py
cbastats/Player.py
cbastats/Team.py
cbastats/__init__.py
cbastats.egg-info/PKG-INFO
cbastats.egg-info/SOURCES.txt
cbastats.egg-info/dependency_links.txt
cbastats.egg-info/requires.txt
cbastats.egg-info/top_level.txt