Metadata-Version: 2.1
Name: cbastats
Version: 0.0.31
Summary: Python package to access CBA stats
Home-page: https://github.com/JJ0131/Cbastats
Author: Jian Jin
Author-email: jjtt0926@gmail.com
License: MIT
Download-URL: https://github.com/JJ0131/Cbastats/archive/v0.0.31.tar.gz
Keywords: CBA,Baseketball
Platform: UNKNOWN
Classifier: Development Status :: 3 - Alpha
Classifier: Intended Audience :: Developers
Classifier: Topic :: Software Development :: Build Tools
Classifier: License :: OSI Approved :: MIT License
Classifier: Programming Language :: Python :: 3
Classifier: Programming Language :: Python :: 3.7
